odoo/addons/storage_media/README.rst
odoo/addons/storage_media/__init__.py
odoo/addons/storage_media/__manifest__.py
odoo/addons/storage_media/data/ir_parameter.xml
odoo/addons/storage_media/i18n/storage_media.pot
odoo/addons/storage_media/models/__init__.py
odoo/addons/storage_media/models/storage_file.py
odoo/addons/storage_media/models/storage_media.py
odoo/addons/storage_media/models/storage_media_type.py
odoo/addons/storage_media/security/ir.model.access.csv
odoo/addons/storage_media/security/ir_rule.xml
odoo/addons/storage_media/security/res_group.xml
odoo/addons/storage_media/static/description/icon.png
odoo/addons/storage_media/tests/__init__.py
odoo/addons/storage_media/tests/test_storage_media.py
odoo/addons/storage_media/views/storage_media_view.xml
odoo13_addon_storage_media-13.0.1.2.0.dist-info/METADATA
odoo13_addon_storage_media-13.0.1.2.0.dist-info/WHEEL
odoo13_addon_storage_media-13.0.1.2.0.dist-info/top_level.txt
odoo13_addon_storage_media-13.0.1.2.0.dist-info/RECORD
