Metadata-Version: 2.1
Name: odoo13-addon-storage-media
Version: 13.0.1.2.0
Summary: Give the posibility to store media data in Odoo
Home-page: https://github.com/OCA/storage
Author: Akretion, Odoo Community Association (OCA)
Author-email: support@odoo-community.org
License: LGPL-3
Platform: UNKNOWN
Classifier: Programming Language :: Python
Classifier: Framework :: Odoo
Classifier: License :: OSI Approved :: GNU Lesser General Public License v3 (LGPLv3)
Requires-Python: >=3.5
Requires-Dist: odoo13-addon-storage-file
Requires-Dist: odoo13-addon-storage-thumbnail
Requires-Dist: odoo (<13.1dev,>=13.0a)
